{
  "feature": "ramadandelight:date_palm_tree",
  "placement": [
    {
      "type": "ramadandelight:configurable_rarity_filter",
      "config_key": "date_palm_tree"
    },
    {
      "type": "ramadandelight:configurable_count",
      "config_key": "date_palm_count"
    },
    {
      "type": "minecraft:in_square"
    },
    {
      "type": "minecraft:heightmap",
      "heightmap": "MOTION_BLOCKING"
    },
    {
      "type": "minecraft:block_predicate_filter",
      "predicate": {
        "type": "minecraft:would_survive",
        "state": {
          "Name": "ramadandelight:palm_sapling",
          "Properties": {
            "stage": "0"
          }
        }
      }
    },
    {
      "type": "minecraft:biome"
    }
  ]
}